pysteel/__init__.py
pysteel-0.0.1.dist-info/METADATA
pysteel-0.0.1.dist-info/WHEEL
pysteel-0.0.1.dist-info/top_level.txt
pysteel-0.0.1.dist-info/RECORD
