Metadata-Version: 2.4
Name: pysteel
Version: 0.0.1
Summary: Project under development
Author-email: Shitao Shi <shi40@illinois.edu>
License: MIT
